[
    {
        "名前": "ヤーク",
        "時代" : "War Age",
        "エリア" : "ヌブールの村",
        "販売情報": {
            "ミニ ブレッド": {
                "価格": 20
            },
            "ミニ ウォーター ボトル": {
                "価格": 15
            },
            "バンテージ": {
                "価格": 8
            },
            "ミルク": {
                "価格": 30
            },
            "クロース シャツ": {
                "価格": 54
            },
            "クロース パンツ": {
                "価格": 54
            },
            "ウッドゥン スティック": {
                "価格": 80
            },
            "ウッド バックラー": {
                "価格": 90
            },
            "ウッドゥン ショートボウ": {
                "価格": 120
            },
            "ウッド アロー": {
                "価格": 1
            },
            "つるはし": {
                "価格": 15
            },
            "スミスハンマー": {
                "価格": 15
            }
        }
    }
]
